itk_cuberille-2.7.2.dist-info/RECORD
itk_cuberille-2.7.2.dist-info/WHEEL
itk_cuberille-2.7.2.dist-info/METADATA
itk_cuberille-2.7.2.dist-info/licenses/LICENSE
itk_cuberille.libs/libtbb-f489fd38.so.12.9
itk/itkCuberilleImageToMeshFilterPython.py
itk/_CuberillePython.abi3.so
itk/CuberillePython.py
itk/Configuration/Cuberille_snake_case.py
itk/Configuration/CuberilleConfig.py
